MANIFEST.in
README.md
setup.py
bin/pdfparanoia
pdfparanoia/__init__.py
pdfparanoia/core.py
pdfparanoia/eraser.py
pdfparanoia/parser.py
pdfparanoia/plugin.py
pdfparanoia/utils.py
pdfparanoia.egg-info/PKG-INFO
pdfparanoia.egg-info/SOURCES.txt
pdfparanoia.egg-info/dependency_links.txt
pdfparanoia.egg-info/not-zip-safe
pdfparanoia.egg-info/requires.txt
pdfparanoia.egg-info/top_level.txt
pdfparanoia/plugins/__init__.py
pdfparanoia/plugins/aip.py
pdfparanoia/plugins/ieee.py
pdfparanoia/plugins/jstor.py
pdfparanoia/plugins/rsc.py
pdfparanoia/plugins/sciencemagazine.py
tests/test_aip.py
tests/test_aip.pyc
tests/test_eraser.py
tests/test_eraser.pyc
tests/test_ieee.py
tests/test_ieee.pyc
tests/test_jstor.py
tests/test_jstor.pyc
tests/test_rsc.py
tests/test_rsc.pyc
tests/test_spie.py
tests/test_spie.pyc